{"cameraMode":{"drawMode":0,"name":"Shaded","section":"Shading Mode"},"sceneLighting":true,"audioPlay":false,"sceneViewState":{"m_AlwaysRefresh":false,"showFog":true,"showSkybox":true,"showFlares":true,"showImageEffects":true,"showParticleSystems":true,"showVisualEffectGraphs":true,"m_FxEnabled":true},"in2DMode":false,"pivot":{"x":-9.23859977722168,"y":6.702569961547852,"z":-1.2627856731414796},"rotation":{"x":0.036849260330200198,"y":-0.9342771172523499,"z":0.10129620879888535,"w":0.3398720324039459},"size":17.16864776611328,"orthographic":true}