{"cameraMode":{"drawMode":0,"name":"Shaded","section":"Shading Mode"},"sceneLighting":true,"audioPlay":false,"sceneViewState":{"m_AlwaysRefresh":true,"showFog":false,"showSkybox":true,"showFlares":true,"showImageEffects":true,"showParticleSystems":true,"showVisualEffectGraphs":true,"m_FxEnabled":true},"in2DMode":false,"pivot":{"x":-25.74707794189453,"y":9.293987274169922,"z":19.524375915527345},"rotation":{"x":-0.140237957239151,"y":-0.7260059118270874,"z":0.15542322397232057,"w":-0.6550600528717041},"size":14.075285911560059,"orthographic":true}